imgur_scraper/__init__.py
imgur_scraper/imgur_scraper.py
imgur_scraper/utils.py
imgur_scraper-0.1.2.dist-info/DESCRIPTION.rst
imgur_scraper-0.1.2.dist-info/METADATA
imgur_scraper-0.1.2.dist-info/RECORD
imgur_scraper-0.1.2.dist-info/WHEEL
imgur_scraper-0.1.2.dist-info/metadata.json
imgur_scraper-0.1.2.dist-info/top_level.txt
