Metadata-Version: 2.0
Name: imgur-scraper
Version: 0.1.2
Summary: Retrieve Imgur's viral posts from a given date (it goes back years).
Home-page: https://github.com/saadmanrafat/imgur-scraper
Author: Saadman Rafat
Author-email: saadmanhere@gmail.com
License: MIT
Platform: UNKNOWN
Classifier: License :: OSI Approved :: MIT License
Classifier: Programming Language :: Python
Classifier: Programming Language :: Python :: 3
Classifier: Programming Language :: Python :: 3.6
Classifier: Programming Language :: Python :: Implementation :: CPython
Classifier: Programming Language :: Python :: Implementation :: PyPy
Requires-Python: >=3.6.0
Requires-Dist: requests-html
